{
  "date": "2025-11-12",
  "generated_at": "2025-11-12T16:59:08.155Z",
  "total_cycles": 452,
  "total_events": 52224,
  "cognitive_load_avg": 0.5584490740740741,
  "hours": [
    {
      "hour": 0,
      "timestamp": "2025-11-11T23:56:34.572Z",
      "pattern": "Consistent feature development (53 features) indicates healthy product iteration and experimentation",
      "pattern_confidence": 0.8625,
      "forecast": "Review and document: Frequent kernel architecture commits (21 commits) indicate active evolution of core reasoning infrastructure",
      "forecast_confidence": 0.65,
      "intent": "chore",
      "cycles_count": 6,
      "events_count": 48,
      "cognitive_load": 0.016666666666666666,
      "files": []
    },
    {
      "hour": 1,
      "timestamp": "2025-11-12T00:56:40.676Z",
      "pattern": "Consistent feature development (53 features) indicates healthy product iteration and experimentation",
      "pattern_confidence": 0.8625,
      "forecast": "Review and document: Frequent kernel architecture commits (21 commits) indicate active evolution of core reasoning infrastructure",
      "forecast_confidence": 0.65,
      "intent": "chore",
      "cycles_count": 11,
      "events_count": 88,
      "cognitive_load": 0.030555555555555555,
      "files": []
    },
    {
      "hour": 2,
      "timestamp": "2025-11-12T01:57:03.543Z",
      "pattern": "Consistent feature development (53 features) indicates healthy product iteration and experimentation",
      "pattern_confidence": 0.8625,
      "forecast": "Review and document: Frequent kernel architecture commits (21 commits) indicate active evolution of core reasoning infrastructure",
      "forecast_confidence": 0.65,
      "intent": "chore",
      "cycles_count": 7,
      "events_count": 56,
      "cognitive_load": 0.019444444444444445,
      "files": []
    },
    {
      "hour": 3,
      "timestamp": "2025-11-12T02:46:28.528Z",
      "pattern": "Consistent feature development (53 features) indicates healthy product iteration and experimentation",
      "pattern_confidence": 0.8625,
      "forecast": "Review and document: Frequent kernel architecture commits (21 commits) indicate active evolution of core reasoning infrastructure",
      "forecast_confidence": 0.65,
      "intent": "chore",
      "cycles_count": 4,
      "events_count": 32,
      "cognitive_load": 0.011111111111111112,
      "files": []
    },
    {
      "hour": 4,
      "timestamp": "2025-11-12T03:50:43.888Z",
      "pattern": "Consistent feature development (53 features) indicates healthy product iteration and experimentation",
      "pattern_confidence": 0.8625,
      "forecast": "Review and document: Frequent kernel architecture commits (21 commits) indicate active evolution of core reasoning infrastructure",
      "forecast_confidence": 0.65,
      "intent": "chore",
      "cycles_count": 5,
      "events_count": 40,
      "cognitive_load": 0.013888888888888888,
      "files": []
    },
    {
      "hour": 5,
      "timestamp": "2025-11-12T04:47:30.507Z",
      "pattern": "Consistent feature development (53 features) indicates healthy product iteration and experimentation",
      "pattern_confidence": 0.8625,
      "forecast": "Review and document: Frequent kernel architecture commits (21 commits) indicate active evolution of core reasoning infrastructure",
      "forecast_confidence": 0.65,
      "intent": "chore",
      "cycles_count": 6,
      "events_count": 48,
      "cognitive_load": 0.016666666666666666,
      "files": []
    },
    {
      "hour": 6,
      "timestamp": "2025-11-12T05:54:44.500Z",
      "pattern": "Consistent feature development (53 features) indicates healthy product iteration and experimentation",
      "pattern_confidence": 0.8625,
      "forecast": "Review and document: Frequent kernel architecture commits (21 commits) indicate active evolution of core reasoning infrastructure",
      "forecast_confidence": 0.65,
      "intent": "chore",
      "cycles_count": 8,
      "events_count": 64,
      "cognitive_load": 0.022222222222222223,
      "files": []
    },
    {
      "hour": 7,
      "timestamp": "2025-11-11T06:48:13.704Z",
      "pattern": "Consistent feature development (53 features) indicates healthy product iteration and experimentation",
      "pattern_confidence": 0.8625,
      "forecast": "Review and document: Frequent kernel architecture commits (21 commits) indicate active evolution of core reasoning infrastructure",
      "forecast_confidence": 0.65,
      "intent": "feature",
      "cycles_count": 3,
      "events_count": 24,
      "cognitive_load": 0.008333333333333333,
      "files": []
    },
    {
      "hour": 8,
      "timestamp": "2025-11-12T07:55:46.514Z",
      "pattern": "Consistent feature development (53 features) indicates healthy product iteration and experimentation",
      "pattern_confidence": 0.8625,
      "forecast": "Review and document: Frequent kernel architecture commits (21 commits) indicate active evolution of core reasoning infrastructure",
      "forecast_confidence": 0.65,
      "intent": "chore",
      "cycles_count": 6,
      "events_count": 48,
      "cognitive_load": 0.016666666666666666,
      "files": [
        "extension/webview/ui/src/App.tsx",
        "reasoning-layer-rl4-2.0.25.vsix",
        "extension/webview/ui/src/App.css"
      ]
    },
    {
      "hour": 9,
      "timestamp": "2025-11-11T08:41:06.281Z",
      "pattern": "Consistent feature development (53 features) indicates healthy product iteration and experimentation",
      "pattern_confidence": 0.8625,
      "forecast": "Review and document: Frequent kernel architecture commits (21 commits) indicate active evolution of core reasoning infrastructure",
      "forecast_confidence": 0.65,
      "intent": "feature",
      "cycles_count": 336,
      "events_count": 2688,
      "cognitive_load": 0.9333333333333333,
      "files": [
        "extension/kernel/cognitive/PatternEvolutionTracker.ts",
        "extension/kernel/indexer/SnapshotRotation.ts",
        "extension/kernel/api/StateReconstructor.ts"
      ]
    },
    {
      "hour": 10,
      "timestamp": "2025-11-11T09:12:52.588Z",
      "pattern": "Consistent feature development (53 features) indicates healthy product iteration and experimentation",
      "pattern_confidence": 0.8625,
      "forecast": "Review and document: Frequent kernel architecture commits (21 commits) indicate active evolution of core reasoning infrastructure",
      "forecast_confidence": 0.65,
      "intent": "feature",
      "cycles_count": 642,
      "events_count": 5136,
      "cognitive_load": 1,
      "files": [
        "extension/kernel/cognitive/PatternEvolutionTracker.ts",
        "extension/kernel/indexer/SnapshotRotation.ts",
        "extension/kernel/api/StateReconstructor.ts"
      ]
    },
    {
      "hour": 11,
      "timestamp": "2025-11-12T10:59:50.302Z",
      "pattern": "Consistent feature development (53 features) indicates healthy product iteration and experimentation",
      "pattern_confidence": 0.8625,
      "forecast": "Review and document: Frequent kernel architecture commits (21 commits) indicate active evolution of core reasoning infrastructure",
      "forecast_confidence": 0.65,
      "intent": "chore",
      "cycles_count": 923,
      "events_count": 5736,
      "cognitive_load": 1,
      "files": [
        "TASKS_RL4.md",
        "DEV_CONTINUITY_MANIFEST.md",
        "plan.md"
      ]
    },
    {
      "hour": 12,
      "timestamp": "2025-11-12T11:13:10.589Z",
      "pattern": "Consistent feature development (53 features) indicates healthy product iteration and experimentation",
      "pattern_confidence": 0.8625,
      "forecast": "Review and document: Frequent kernel architecture commits (21 commits) indicate active evolution of core reasoning infrastructure",
      "forecast_confidence": 0.65,
      "intent": "chore",
      "cycles_count": 1050,
      "events_count": 6396,
      "cognitive_load": 1,
      "files": [
        "TASKS_RL4.md",
        "DEV_CONTINUITY_MANIFEST.md",
        "plan.md"
      ]
    },
    {
      "hour": 13,
      "timestamp": "2025-11-10T12:56:22.052Z",
      "pattern": "Consistent feature development (53 features) indicates healthy product iteration and experimentation",
      "pattern_confidence": 0.8625,
      "forecast": "Review and document: Frequent kernel architecture commits (21 commits) indicate active evolution of core reasoning infrastructure",
      "forecast_confidence": 0.65,
      "intent": "test",
      "cycles_count": 746,
      "events_count": 4784,
      "cognitive_load": 1,
      "files": [
        "extension/kernel/cognitive/CorrelationEngine.ts",
        "reasoning-layer-rl4-2.0.6.vsix",
        "rl4-backup-stable-v206-working-pipeline.tar.gz"
      ]
    },
    {
      "hour": 14,
      "timestamp": "2025-11-10T13:59:54.517Z",
      "pattern": "Consistent feature development (53 features) indicates healthy product iteration and experimentation",
      "pattern_confidence": 0.8625,
      "forecast": "Review and document: Frequent kernel architecture commits (21 commits) indicate active evolution of core reasoning infrastructure",
      "forecast_confidence": 0.65,
      "intent": "feature",
      "cycles_count": 948,
      "events_count": 7564,
      "cognitive_load": 1,
      "files": [
        "extension/kernel/cognitive/CorrelationEngine.ts",
        "reasoning-layer-rl4-2.0.6.vsix",
        "rl4-backup-stable-v206-working-pipeline.tar.gz"
      ]
    },
    {
      "hour": 15,
      "timestamp": "2025-11-10T14:51:35.816Z",
      "pattern": "Consistent feature development (53 features) indicates healthy product iteration and experimentation",
      "pattern_confidence": 0.8625,
      "forecast": "Review and document: Frequent kernel architecture commits (21 commits) indicate active evolution of core reasoning infrastructure",
      "forecast_confidence": 0.65,
      "intent": "feature",
      "cycles_count": 440,
      "events_count": 3520,
      "cognitive_load": 1,
      "files": [
        "reasoning-layer-rl4-2.0.6.vsix",
        "INSTALL_v2.0.6_FIXES.md",
        "RELOAD_CURSOR.txt"
      ]
    },
    {
      "hour": 16,
      "timestamp": "2025-11-10T15:59:56.023Z",
      "pattern": "Consistent feature development (53 features) indicates healthy product iteration and experimentation",
      "pattern_confidence": 0.8625,
      "forecast": "Review and document: Frequent kernel architecture commits (21 commits) indicate active evolution of core reasoning infrastructure",
      "forecast_confidence": 0.65,
      "intent": "feature",
      "cycles_count": 717,
      "events_count": 5736,
      "cognitive_load": 1,
      "files": [
        "TASKS_RL4.md",
        "E2_TOOLING_COMPLETE.md",
        "extension/extension.ts"
      ]
    },
    {
      "hour": 17,
      "timestamp": "2025-11-10T16:18:36.320Z",
      "pattern": "Consistent feature development (53 features) indicates healthy product iteration and experimentation",
      "pattern_confidence": 0.8625,
      "forecast": "Review and document: Frequent kernel architecture commits (21 commits) indicate active evolution of core reasoning infrastructure",
      "forecast_confidence": 0.65,
      "intent": "feature",
      "cycles_count": 852,
      "events_count": 5600,
      "cognitive_load": 1,
      "files": [
        "RL4_DATA_STRUCTURE_GUIDE.md",
        "scripts/export-rl4-snapshot.sh",
        "rl4-snapshot.json"
      ]
    },
    {
      "hour": 18,
      "timestamp": "2025-11-11T17:43:42.825Z",
      "pattern": "Consistent feature development (53 features) indicates healthy product iteration and experimentation",
      "pattern_confidence": 0.8625,
      "forecast": "Review and document: Frequent kernel architecture commits (21 commits) indicate active evolution of core reasoning infrastructure",
      "forecast_confidence": 0.65,
      "intent": "chore",
      "cycles_count": 176,
      "events_count": 176,
      "cognitive_load": 0.4888888888888889,
      "files": [
        "extension/webview/ui/src/components/ui/Tabs.tsx",
        "reasoning-layer-rl4-2.0.18.vsix",
        "reasoning-layer-rl4-2.0.16.vsix"
      ]
    },
    {
      "hour": 19,
      "timestamp": "2025-11-03T18:53:27.963Z",
      "pattern": "Consistent feature development (53 features) indicates healthy product iteration and experimentation",
      "pattern_confidence": 0.8625,
      "forecast": "Review and document: Frequent kernel architecture commits (21 commits) indicate active evolution of core reasoning infrastructure",
      "forecast_confidence": 0.65,
      "intent": "fix",
      "cycles_count": 595,
      "events_count": 1952,
      "cognitive_load": 1,
      "files": [
        "extension/extension.ts",
        "extension/kernel/CognitiveScheduler.ts",
        "package.json"
      ]
    },
    {
      "hour": 20,
      "timestamp": "2025-11-11T19:49:55.794Z",
      "pattern": "Consistent feature development (53 features) indicates healthy product iteration and experimentation",
      "pattern_confidence": 0.8625,
      "forecast": "Review and document: Frequent kernel architecture commits (21 commits) indicate active evolution of core reasoning infrastructure",
      "forecast_confidence": 0.65,
      "intent": "chore",
      "cycles_count": 524,
      "events_count": 1408,
      "cognitive_load": 1,
      "files": [
        "package.json",
        "reasoning-layer-rl4-2.0.10.vsix",
        "reasoning-layer-rl4-2.0.19-FINAL.vsix"
      ]
    },
    {
      "hour": 21,
      "timestamp": "2025-11-03T20:42:40.842Z",
      "pattern": "Consistent feature development (53 features) indicates healthy product iteration and experimentation",
      "pattern_confidence": 0.8625,
      "forecast": "Review and document: Frequent kernel architecture commits (21 commits) indicate active evolution of core reasoning infrastructure",
      "forecast_confidence": 0.65,
      "intent": "feature",
      "cycles_count": 65,
      "events_count": 40,
      "cognitive_load": 0.18055555555555555,
      "files": [
        "extension/kernel/inputs/GitCommitListener.ts",
        "package.json",
        "reasoning-layer-rl4-2.0.3.vsix"
      ]
    },
    {
      "hour": 22,
      "timestamp": "2025-11-03T21:59:50.284Z",
      "pattern": "Consistent feature development (53 features) indicates healthy product iteration and experimentation",
      "pattern_confidence": 0.8625,
      "forecast": "Review and document: Frequent kernel architecture commits (21 commits) indicate active evolution of core reasoning infrastructure",
      "forecast_confidence": 0.65,
      "intent": "feature",
      "cycles_count": 432,
      "events_count": 1024,
      "cognitive_load": 1,
      "files": [
        "scripts/seed-git-history.ts",
        "scripts/seed-git-history.sh",
        "extension/kernel/cognitive/PatternLearningEngine.ts"
      ]
    },
    {
      "hour": 23,
      "timestamp": "2025-11-03T22:38:10.945Z",
      "pattern": "Consistent feature development (53 features) indicates healthy product iteration and experimentation",
      "pattern_confidence": 0.8625,
      "forecast": "Review and document: Frequent kernel architecture commits (21 commits) indicate active evolution of core reasoning infrastructure",
      "forecast_confidence": 0.65,
      "intent": "feature",
      "cycles_count": 232,
      "events_count": 16,
      "cognitive_load": 0.6444444444444445,
      "files": []
    }
  ],
  "top_pattern": "Consistent feature development (53 features) indicates healthy product iteration and experimentation",
  "top_forecast": "Review and document: Frequent kernel architecture commits (21 commits) indicate active evolution of core reasoning infrastructure",
  "dominant_intent": "chore",
  "most_active_hour": 12
}