{
  "date": "2025-11-04",
  "generated_at": "2025-11-10T20:12:25.332Z",
  "total_cycles": 1943,
  "total_events": 5296,
  "cognitive_load_avg": 0.3015046296296296,
  "hours": [
    {
      "hour": 0,
      "timestamp": "2025-11-04T00:00:00Z",
      "pattern": "",
      "pattern_confidence": 0,
      "forecast": "",
      "forecast_confidence": 0,
      "intent": "none",
      "cycles_count": 0,
      "events_count": 0,
      "cognitive_load": 0,
      "files": []
    },
    {
      "hour": 1,
      "timestamp": "2025-11-04T00:59:58.573Z",
      "pattern": "Consistent feature development (53 features) indicates healthy product iteration and experimentation",
      "pattern_confidence": 0.8625,
      "forecast": "Review and document: Consistent feature development (53 features) indicates healthy product iteration and experimentation",
      "forecast_confidence": 0.67,
      "intent": "feature",
      "cycles_count": 360,
      "events_count": 0,
      "cognitive_load": 1,
      "files": []
    },
    {
      "hour": 2,
      "timestamp": "2025-11-04T01:54:44.345Z",
      "pattern": "Consistent feature development (53 features) indicates healthy product iteration and experimentation",
      "pattern_confidence": 0.8625,
      "forecast": "Review and document: Consistent feature development (53 features) indicates healthy product iteration and experimentation",
      "forecast_confidence": 0.67,
      "intent": "feature",
      "cycles_count": 59,
      "events_count": 0,
      "cognitive_load": 0.1638888888888889,
      "files": []
    },
    {
      "hour": 3,
      "timestamp": "2025-11-04T02:59:58.771Z",
      "pattern": "Consistent feature development (53 features) indicates healthy product iteration and experimentation",
      "pattern_confidence": 0.8625,
      "forecast": "Review and document: Consistent feature development (53 features) indicates healthy product iteration and experimentation",
      "forecast_confidence": 0.67,
      "intent": "feature",
      "cycles_count": 68,
      "events_count": 0,
      "cognitive_load": 0.18888888888888888,
      "files": []
    },
    {
      "hour": 4,
      "timestamp": "2025-11-04T03:59:46.904Z",
      "pattern": "Consistent feature development (53 features) indicates healthy product iteration and experimentation",
      "pattern_confidence": 0.8625,
      "forecast": "Review and document: Consistent feature development (53 features) indicates healthy product iteration and experimentation",
      "forecast_confidence": 0.67,
      "intent": "feature",
      "cycles_count": 210,
      "events_count": 0,
      "cognitive_load": 0.5833333333333334,
      "files": []
    },
    {
      "hour": 5,
      "timestamp": "2025-11-04T04:59:58.752Z",
      "pattern": "Consistent feature development (53 features) indicates healthy product iteration and experimentation",
      "pattern_confidence": 0.8625,
      "forecast": "Review and document: Consistent feature development (53 features) indicates healthy product iteration and experimentation",
      "forecast_confidence": 0.67,
      "intent": "feature",
      "cycles_count": 59,
      "events_count": 0,
      "cognitive_load": 0.1638888888888889,
      "files": []
    },
    {
      "hour": 6,
      "timestamp": "2025-11-04T05:56:33.953Z",
      "pattern": "Consistent feature development (53 features) indicates healthy product iteration and experimentation",
      "pattern_confidence": 0.8625,
      "forecast": "Review and document: Consistent feature development (53 features) indicates healthy product iteration and experimentation",
      "forecast_confidence": 0.67,
      "intent": "feature",
      "cycles_count": 122,
      "events_count": 0,
      "cognitive_load": 0.3388888888888889,
      "files": []
    },
    {
      "hour": 7,
      "timestamp": "2025-11-04T06:55:59.793Z",
      "pattern": "Consistent feature development (53 features) indicates healthy product iteration and experimentation",
      "pattern_confidence": 0.8625,
      "forecast": "Review and document: Consistent feature development (53 features) indicates healthy product iteration and experimentation",
      "forecast_confidence": 0.67,
      "intent": "feature",
      "cycles_count": 89,
      "events_count": 0,
      "cognitive_load": 0.24722222222222223,
      "files": []
    },
    {
      "hour": 8,
      "timestamp": "2025-11-04T07:59:52.385Z",
      "pattern": "Consistent feature development (53 features) indicates healthy product iteration and experimentation",
      "pattern_confidence": 0.8625,
      "forecast": "Review and document: Consistent feature development (53 features) indicates healthy product iteration and experimentation",
      "forecast_confidence": 0.67,
      "intent": "feature",
      "cycles_count": 144,
      "events_count": 0,
      "cognitive_load": 0.4,
      "files": []
    },
    {
      "hour": 9,
      "timestamp": "2025-11-04T08:59:53.656Z",
      "pattern": "Consistent feature development (53 features) indicates healthy product iteration and experimentation",
      "pattern_confidence": 0.8625,
      "forecast": "Review and document: Consistent feature development (53 features) indicates healthy product iteration and experimentation",
      "forecast_confidence": 0.67,
      "intent": "feature",
      "cycles_count": 360,
      "events_count": 0,
      "cognitive_load": 1,
      "files": []
    },
    {
      "hour": 10,
      "timestamp": "2025-11-04T09:59:54.882Z",
      "pattern": "Consistent feature development (53 features) indicates healthy product iteration and experimentation",
      "pattern_confidence": 0.8625,
      "forecast": "Review and document: Consistent feature development (53 features) indicates healthy product iteration and experimentation",
      "forecast_confidence": 0.67,
      "intent": "feature",
      "cycles_count": 360,
      "events_count": 0,
      "cognitive_load": 1,
      "files": []
    },
    {
      "hour": 11,
      "timestamp": "2025-11-04T10:18:35.294Z",
      "pattern": "Consistent feature development (53 features) indicates healthy product iteration and experimentation",
      "pattern_confidence": 0.8625,
      "forecast": "Review and document: Consistent feature development (53 features) indicates healthy product iteration and experimentation",
      "forecast_confidence": 0.67,
      "intent": "feature",
      "cycles_count": 112,
      "events_count": 0,
      "cognitive_load": 0.3111111111111111,
      "files": []
    },
    {
      "hour": 12,
      "timestamp": "2025-11-04T12:00:00Z",
      "pattern": "",
      "pattern_confidence": 0,
      "forecast": "",
      "forecast_confidence": 0,
      "intent": "none",
      "cycles_count": 0,
      "events_count": 0,
      "cognitive_load": 0,
      "files": []
    },
    {
      "hour": 13,
      "timestamp": "2025-11-04T13:00:00Z",
      "pattern": "",
      "pattern_confidence": 0,
      "forecast": "",
      "forecast_confidence": 0,
      "intent": "none",
      "cycles_count": 0,
      "events_count": 0,
      "cognitive_load": 0,
      "files": []
    },
    {
      "hour": 14,
      "timestamp": "2025-11-04T14:00:00Z",
      "pattern": "",
      "pattern_confidence": 0,
      "forecast": "",
      "forecast_confidence": 0,
      "intent": "none",
      "cycles_count": 0,
      "events_count": 0,
      "cognitive_load": 0,
      "files": []
    },
    {
      "hour": 15,
      "timestamp": "2025-11-04T15:00:00Z",
      "pattern": "",
      "pattern_confidence": 0,
      "forecast": "",
      "forecast_confidence": 0,
      "intent": "none",
      "cycles_count": 0,
      "events_count": 0,
      "cognitive_load": 0,
      "files": []
    },
    {
      "hour": 16,
      "timestamp": "2025-11-04T16:00:00Z",
      "pattern": "",
      "pattern_confidence": 0,
      "forecast": "",
      "forecast_confidence": 0,
      "intent": "none",
      "cycles_count": 0,
      "events_count": 0,
      "cognitive_load": 0,
      "files": []
    },
    {
      "hour": 17,
      "timestamp": "2025-11-04T17:00:00Z",
      "pattern": "",
      "pattern_confidence": 0,
      "forecast": "",
      "forecast_confidence": 0,
      "intent": "none",
      "cycles_count": 0,
      "events_count": 0,
      "cognitive_load": 0,
      "files": []
    },
    {
      "hour": 18,
      "timestamp": "2025-11-10T17:59:55.023Z",
      "pattern": "Consistent feature development (53 features) indicates healthy product iteration and experimentation",
      "pattern_confidence": 0.8625,
      "forecast": "Review and document: Consistent feature development (53 features) indicates healthy product iteration and experimentation",
      "forecast_confidence": 0.67,
      "intent": "feature",
      "cycles_count": 98,
      "events_count": 784,
      "cognitive_load": 0.2722222222222222,
      "files": [
        "USER_JOURNEY_RL4.md",
        "USER_JOURNEY_VISUAL.md"
      ]
    },
    {
      "hour": 19,
      "timestamp": "2025-11-10T18:59:08.881Z",
      "pattern": "Consistent feature development (53 features) indicates healthy product iteration and experimentation",
      "pattern_confidence": 0.8625,
      "forecast": "Review and document: Consistent feature development (53 features) indicates healthy product iteration and experimentation",
      "forecast_confidence": 0.67,
      "intent": "feature",
      "cycles_count": 219,
      "events_count": 1752,
      "cognitive_load": 0.6083333333333333,
      "files": [
        "WEBVIEW_SPEC_VALIDATION.md",
        "extension/kernel/indexer/CacheIndex.ts",
        "extension/kernel/CognitiveScheduler.ts"
      ]
    },
    {
      "hour": 20,
      "timestamp": "2025-11-10T19:59:57.716Z",
      "pattern": "Consistent feature development (53 features) indicates healthy product iteration and experimentation",
      "pattern_confidence": 0.8625,
      "forecast": "Review and document: Consistent feature development (53 features) indicates healthy product iteration and experimentation",
      "forecast_confidence": 0.67,
      "intent": "feature",
      "cycles_count": 271,
      "events_count": 2168,
      "cognitive_load": 0.7527777777777778,
      "files": [
        "WEBVIEW_SPEC_VALIDATION.md",
        "extension/kernel/indexer/CacheIndex.ts",
        "extension/kernel/CognitiveScheduler.ts"
      ]
    },
    {
      "hour": 21,
      "timestamp": "2025-11-10T20:12:17.914Z",
      "pattern": "Consistent feature development (53 features) indicates healthy product iteration and experimentation",
      "pattern_confidence": 0.8625,
      "forecast": "Review and document: Consistent feature development (53 features) indicates healthy product iteration and experimentation",
      "forecast_confidence": 0.67,
      "intent": "feature",
      "cycles_count": 74,
      "events_count": 592,
      "cognitive_load": 0.20555555555555555,
      "files": [
        "WEBVIEW_SPEC_VALIDATION.md",
        "extension/kernel/indexer/CacheIndex.ts",
        "extension/kernel/CognitiveScheduler.ts"
      ]
    },
    {
      "hour": 22,
      "timestamp": "2025-11-04T22:00:00Z",
      "pattern": "",
      "pattern_confidence": 0,
      "forecast": "",
      "forecast_confidence": 0,
      "intent": "none",
      "cycles_count": 0,
      "events_count": 0,
      "cognitive_load": 0,
      "files": []
    },
    {
      "hour": 23,
      "timestamp": "2025-11-04T23:00:00Z",
      "pattern": "",
      "pattern_confidence": 0,
      "forecast": "",
      "forecast_confidence": 0,
      "intent": "none",
      "cycles_count": 0,
      "events_count": 0,
      "cognitive_load": 0,
      "files": []
    }
  ],
  "top_pattern": "Consistent feature development (53 features) indicates healthy product iteration and experimentation",
  "top_forecast": "Review and document: Consistent feature development (53 features) indicates healthy product iteration and experimentation",
  "dominant_intent": "feature",
  "most_active_hour": 1
}